collector/__init__.py
collector/action_config.yml
collector/domain_config.py
collector/emr_data_collector.py
emr_metadata_collector-1.0.3.data/scripts/emr_metadata_collector
emr_metadata_collector-1.0.3.dist-info/METADATA
emr_metadata_collector-1.0.3.dist-info/WHEEL
emr_metadata_collector-1.0.3.dist-info/top_level.txt
emr_metadata_collector-1.0.3.dist-info/RECORD
