Metadata-Version: 2.1
Name: emr-metadata-collector
Version: 1.0.3
Summary: EMr metadata collector for operational review
Home-page: UNKNOWN
Author: Jianwei Li
Author-email: lijianwe@amazon.com
License: UNKNOWN
Platform: UNKNOWN
Requires-Dist: requests
Requires-Dist: requests-aws4auth
Requires-Dist: boto3
Requires-Dist: pyyaml
